{
    "n_por_grado": {
        "Civil": 32,
        "Informática": 25,
        "Ejecución": 7,
        "Total": 64
    },
    "metricas_supervisadas": {
        "modelo_ganador": "7. Random Forest",
        "accuracy": 0.9279000000000001,
        "tecnica_balanceo": "SMOTE (Synthetic Minority Over-sampling Technique)",
        "nota": "El modelo LDA se mantiene de forma interna exclusivamente para la proyección espacial 2D."
    },
    "analisis_homogeneidad": {
        "nota": "Consultar el archivo 'similitud_centroides.png' para la evaluación de distancias inter-centroides.",
        "test_permutacion_p_valor": 0.0,
        "significancia": "Estadísticamente significativo (p < 0.05)"
    },
    "terminos_distintivos": {
        "Civil": [
            "ingeniería civil",
            "civil computación",
            "fundamento",
            "disciplina",
            "económico social",
            "tecnología información",
            "ingeniera",
            "identificar",
            "admisión",
            "comunicar él",
            "inglés",
            "institucional",
            "civil informático",
            "idioma inglés",
            "gestión proyecto"
        ],
        "Ejecución": [
            "gestión",
            "institución",
            "eficiencia",
            "analizar",
            "sistema información",
            "adaptar",
            "visión cristiano",
            "tic",
            "adaptar él",
            "mundo",
            "cristiano",
            "comunidad",
            "ingeniero ejecución",
            "matemática",
            "distinguir"
        ],
        "Informática": [
            "informática chile",
            "industrial",
            "formar profesional",
            "chile",
            "educación",
            "ciberseguridad",
            "sector productivo",
            "respuesta",
            "empresarial",
            "función",
            "in",
            "práctica industria",
            "necesidad organización",
            "phd",
            "continuo"
        ]
    }
}